app_runtime-0.0.0.dist-info/licenses/LICENSE
runtime/__init__.py
runtime/application.py
runtime/locking.py
runtime/modules.py
runtime/py.typed
runtime/user.py
runtime/core/modules.py
runtime/core/application/__init__.py
runtime/core/application/hook_terminate.py
runtime/core/application/log.py
runtime/core/application/prevent_pythonpath.py
runtime/core/application/single_instance_exception.py
runtime/core/application/terminate_exception.py
runtime/core/compat/fcntl.py
runtime/core/compat/grp.py
runtime/core/compat/msvcrt.py
runtime/core/compat/os.py
runtime/core/locking/__init__.py
runtime/core/locking/handle.py
runtime/core/locking/lock_exception.py
runtime/core/locking/log.py
runtime/core/objects/lifetime/finalizable.py
runtime/core/objects/lifetime/finalized_error.py
runtime/core/user/__init__.py
runtime/core/user/log.py
runtime/objects/lifetime.py
app_runtime-0.0.0.dist-info/METADATA
app_runtime-0.0.0.dist-info/WHEEL
app_runtime-0.0.0.dist-info/top_level.txt
app_runtime-0.0.0.dist-info/RECORD
